{
    "metadata": {
        "code": 123,
        "name": "user",
        "data": "User data",
        "date": "2021-03-01",
        "myimage": "a1.jpg",
    
        "mytable": [
            {"product": "car10",
            "brand": "b1",
            "model": "m1",
            "price": "12000"},
            {"product": "car20",
            "brand": "b2",
            "model": "m2",
            "price": "32000"},
            {"product": "car30",
            "brand": "b3",
            "model": "m3",
            "price": "45000"},
            {"product": "car40",
            "brand": "b4",
            "model": "compass",
            "price": "m4"}
        ]

    }
}